[
  {
    "id": 1,
    "title": "Futsal — First Division vs. Obras",
    "category": "Sports",
    "date": "2025-04-26",
    "time": "18:00",
    "location": "CABNA — Main Court",
    "description": "Senior futsal league matchday. Come support the first team in this important home fixture.",
    "status": "Upcoming",
    "image": "https://clubbanconacion.org.ar/storage/banners/o57DsBjcuttzgg7490OG0vrVYXaMDFAQHAp04DYa.jpg"
  },
  {
    "id": 2,
    "title": "Youth Basketball Tournament",
    "category": "Sports",
    "date": "2025-04-27",
    "time": "10:00",
    "location": "CABNA — Sports Hall",
    "description": "Inter-club youth basketball tournament. All categories. Free entry for spectators.",
    "status": "Free Entry",
    "image": "https://clubbanconacion.org.ar/storage/banners/OhQmF3Vc1q1ymT2H8zz1Eqvco0RTPsMX25VkTYc5.jpg"
  },
  {
    "id": 3,
    "title": "Family Fun Day & Open House",
    "category": "Family",
    "date": "2025-05-18",
    "time": "11:00",
    "location": "CABNA — Full Campus",
    "description": "A day of games, shows, and activities for the whole family. Open to the public.",
    "status": "Free Entry",
    "image": "https://clubbanconacion.org.ar/assets/img/home/actividades.jpg"
  },
  {
    "id": 4,
    "title": "Artistic Gymnastics Exhibition",
    "category": "Sports",
    "date": "2025-06-07",
    "time": "15:00",
    "location": "CABNA — Gymnasium",
    "description": "Annual exhibition by the formative gymnastics categories. All are welcome.",
    "status": "Upcoming",
    "image": "https://clubbanconacion.org.ar/assets/img/club/portada.jpg"
  },
  {
    "id": 5,
    "title": "Annual Members' Asado",
    "category": "Social",
    "date": "2025-06-20",
    "time": "20:00",
    "location": "CABNA — Quinchos",
    "description": "The traditional end-of-semester asado for members and their families. Reserve your spot.",
    "status": "Members Only",
    "image": "https://clubbanconacion.org.ar/assets/img/home/video.jpg"
  },
  {
    "id": 6,
    "title": "Outdoor Yoga Session",
    "category": "Health & Wellness",
    "date": "2025-04-05",
    "time": "08:30",
    "location": "CABNA — Park",
    "description": "Special open-air yoga session for the whole family. All levels welcome.",
    "status": "Free Entry",
    "image": "https://clubbanconacion.org.ar/assets/img/home/deportes.jpg"
  },
  {
    "id": 7,
    "title": "Football 11 League — Matchday",
    "category": "Sports",
    "date": "2025-04-12",
    "time": "15:00",
    "location": "CABNA — Football Pitch",
    "description": "ABAD league matchday. First division. Come cheer on the squad.",
    "status": "Upcoming",
    "image": "https://clubbanconacion.org.ar/storage/banners/qPWqGjvvpszaapDlVD7d7zncwCoU0zqVCUgRXqNr.jpg"
  },
  {
    "id": 8,
    "title": "Pilates MAT Open Class",
    "category": "Health & Wellness",
    "date": "2025-04-22",
    "time": "10:00",
    "location": "CABNA — Multipurpose Hall",
    "description": "Introductory Pilates MAT class. Open to members and non-members.",
    "status": "Free Entry",
    "image": "https://clubbanconacion.org.ar/assets/img/actividades/portada.jpg"
  },
  {
    "id": 9,
    "title": "Table Tennis Open Tournament",
    "category": "Sports",
    "date": "2025-05-03",
    "time": "11:00",
    "location": "CABNA — Table Tennis Hall",
    "description": "Open table tennis tournament. Youth and adult categories.",
    "status": "Upcoming",
    "image": "https://clubbanconacion.org.ar/assets/img/deportes/portada.jpg"
  },
  {
    "id": 10,
    "title": "Quincho Open Day",
    "category": "Family",
    "date": "2025-06-01",
    "time": "12:00",
    "location": "CABNA — Quinchos",
    "description": "Open day to visit and explore the club's quincho and BBQ area. Open to everyone.",
    "status": "Free Entry",
    "image": "https://clubbanconacion.org.ar/assets/img/club/galeria/8.jpg"
  },
  {
    "id": 11,
    "title": "Aquagym Special Session",
    "category": "Health & Wellness",
    "date": "2025-06-15",
    "time": "09:00",
    "location": "CABNA — Heated Pool",
    "description": "Special aquagym session open to the whole community.",
    "status": "Free Entry",
    "image": "https://clubbanconacion.org.ar/assets/img/club/galeria/3.jpg"
  },
  {
    "id": 12,
    "title": "Basketball Championship",
    "category": "Sports",
    "date": "2025-09-20",
    "time": "17:00",
    "location": "CABNA — Sports Hall",
    "description": "Inter-club basketball championship. All categories represented.",
    "status": "Upcoming",
    "image": "https://clubbanconacion.org.ar/storage/banners/OhQmF3Vc1q1ymT2H8zz1Eqvco0RTPsMX25VkTYc5.jpg"
  }
]
